{
	"custdata": [
	{
		"_id": "57b3f46b5ce286136c332fcf",
		"index": 0,
		"age": 39,
		"eyeColor": "green",
		"name": "Payne Fox",
		"gender": "male",
		"email": "paynefox@euron.com",
		"phone": "+1 (811) 409-3859"
	},

	{
		"_id": "57b3f46b77949b6473777232",
		"index": 1,
		"age": 34,
		"eyeColor": "blue",
		"name": "Carmela Washington",
		"gender": "female",
		"email": "carmelawashington@euron.com",
		"phone": "+1 (911) 457-2680"
	},

	{
		"_id": "57b3f46b47516700710ebcf4",
		"index": 2,
		"age": 28,
		"eyeColor": "blue",
		"name": "Sargent Carlson",
		"gender": "male",
		"email": "sargentcarlson@euron.com",
		"phone": "+1 (936) 483-2767"
	},

	{
		"_id": "57b3f46b56fb99329105314c",
		"index": 3,
		"age": 28,
		"eyeColor": "blue",
		"name": "Weiss Britt",
		"gender": "male",
		"email": "weissbritt@euron.com",
		"phone": "+1 (992) 413-2723"
	},

	{
		"_id": "57b3f46bfacf94a69277a367",
		"index": 4,
		"age": 30,
		"eyeColor": "green",
		"name": "Mamie Hood",
		"gender": "female",
		"email": "mamiehood@euron.com",
		"phone": "+1 (951) 424-2362"
	},

	{
		"_id": "57b3f46b4d3b23b87c184b02",
		"index": 5,
		"age": 32,
		"eyeColor": "brown",
		"name": "Chang Jefferson",
		"gender": "male",
		"email": "changjefferson@euron.com",
		"phone": "+1 (993) 586-3188"
	},

	{
		"_id": "57b3f46be08a571cb4612775",
		"index": 6,
		"age": 30,
		"eyeColor": "brown",
		"name": "Hale Harrison",
		"gender": "male",
		"email": "haleharrison@euron.com",
		"phone": "+1 (950) 465-3873"
	},

	{
		"_id": "57b3f46b91b2597b044da87b",
		"index": 7,
		"age": 30,
		"eyeColor": "green",
		"name": "Nell Singleton",
		"gender": "female",
		"email": "nellsingleton@euron.com",
		"phone": "+1 (903) 472-3632"
	},

	{
		"_id": "57b3f46b5186feadba1da9e0",
		"index": 8,
		"age": 34,
		"eyeColor": "blue",
		"name": "Kelsey Delgado",
		"gender": "female",
		"email": "kelseydelgado@euron.com",
		"phone": "+1 (980) 533-2917"
	},

	{
		"_id": "57b3f46bf0838d75c1013661",
		"index": 9,
		"age": 27,
		"eyeColor": "blue",
		"name": "Blackburn Holman",
		"gender": "male",
		"email": "blackburnholman@euron.com",
		"phone": "+1 (906) 533-2728"
	},

	{
		"_id": "57b3f46bf3db67f94d6e0ffc",
		"index": 10,
		"age": 40,
		"eyeColor": "green",
		"name": "Lina Summers",
		"gender": "female",
		"email": "linasummers@euron.com",
		"phone": "+1 (953) 530-2234"
	},

	{
		"_id": "57b3f46b89d451a397f292a8",
		"index": 11,
		"age": 38,
		"eyeColor": "blue",
		"name": "Velasquez Randall",
		"gender": "male",
		"email": "velasquezrandall@euron.com",
		"phone": "+1 (990) 427-2567"
	},

	{
		"_id": "57b3f46bfb8d9d0c8550ddb7",
		"index": 12,
		"age": 31,
		"eyeColor": "brown",
		"name": "Rosalinda Hodge",
		"gender": "female",
		"email": "rosalindahodge@euron.com",
		"phone": "+1 (984) 561-3246"
	},

	{
		"_id": "57b3f46b6f21ecc243a8f39d",
		"index": 13,
		"age": 25,
		"eyeColor": "blue",
		"name": "Madden Ortiz",
		"gender": "male",
		"email": "maddenortiz@euron.com",
		"phone": "+1 (970) 490-3464"
	},

	{
		"_id": "57b3f46bc66c6401426d6797",
		"index": 14,
		"age": 33,
		"eyeColor": "brown",
		"name": "Vonda Edwards",
		"gender": "female",
		"email": "vondaedwards@euron.com",
		"phone": "+1 (905) 438-2149"
	},

	{
		"_id": "57b3f46b5cd05b9155cf8753",
		"index": 15,
		"age": 30,
		"eyeColor": "blue",
		"name": "Summers Poole",
		"gender": "male",
		"email": "summerspoole@euron.com",
		"phone": "+1 (972) 567-3964"
	},

	{
		"_id": "57b3f46b202e9d64a954167c",
		"index": 16,
		"age": 36,
		"eyeColor": "brown",
		"name": "Nash Dorsey",
		"gender": "male",
		"email": "nashdorsey@euron.com",
		"phone": "+1 (985) 537-2650"
	},

	{
		"_id": "57b3f46b26db49cbdbf3b97a",
		"index": 17,
		"age": 35,
		"eyeColor": "blue",
		"name": "Marva Whitaker",
		"gender": "female",
		"email": "marvawhitaker@euron.com",
		"phone": "+1 (968) 453-3540"
	},

	{
		"_id": "57b3f46bac370d4f3cf748ce",
		"index": 18,
		"age": 20,
		"eyeColor": "green",
		"name": "Dena Thornton",
		"gender": "female",
		"email": "denathornton@euron.com",
		"phone": "+1 (875) 527-2098"
	},

	{
		"_id": "57b3f46b355e2e7ef516ab54",
		"index": 19,
		"age": 31,
		"eyeColor": "green",
		"name": "Violet Conner",
		"gender": "female",
		"email": "violetconner@euron.com",
		"phone": "+1 (996) 532-3596"
	},

	{
		"_id": "57b3f46bb4139b7ce8e75462",
		"index": 20,
		"age": 20,
		"eyeColor": "brown",
		"name": "Yvette Mcdowell",
		"gender": "female",
		"email": "yvettemcdowell@euron.com",
		"phone": "+1 (898) 428-2366"
	},

	{
		"_id": "57b3f46b7ff62b29eac23cea",
		"index": 21,
		"age": 26,
		"eyeColor": "brown",
		"name": "Colette Moreno",
		"gender": "female",
		"email": "colettemoreno@euron.com",
		"phone": "+1 (913) 481-3232"
	},

	{
		"_id": "57b3f46bb464c0bb3062283b",
		"index": 22,
		"age": 34,
		"eyeColor": "green",
		"name": "Huff Burks",
		"gender": "male",
		"email": "huffburks@euron.com",
		"phone": "+1 (911) 598-3475"
	},

	{
		"_id": "57b3f46b3118337e93933f79",
		"index": 23,
		"age": 26,
		"eyeColor": "brown",
		"name": "Lana Dickerson",
		"gender": "female",
		"email": "lanadickerson@euron.com",
		"phone": "+1 (918) 506-2479"
	},

	{
		"_id": "57b3f46b5df73bec7b9fb739",
		"index": 24,
		"age": 35,
		"eyeColor": "blue",
		"name": "Claudine Crosby",
		"gender": "female",
		"email": "claudinecrosby@euron.com",
		"phone": "+1 (963) 545-2240"
	},

	{
		"_id": "57b3f46be713cf4e8f05b942",
		"index": 25,
		"age": 22,
		"eyeColor": "blue",
		"name": "Cristina Ward",
		"gender": "female",
		"email": "cristinaward@euron.com",
		"phone": "+1 (911) 439-3010"
	},

	{
		"_id": "57b3f46becbcbffab42b5487",
		"index": 26,
		"age": 37,
		"eyeColor": "brown",
		"name": "Juanita Freeman",
		"gender": "female",
		"email": "juanitafreeman@euron.com",
		"phone": "+1 (942) 589-3061"
	},

	{
		"_id": "57b3f46bf13bcc5387d964b8",
		"index": 27,
		"age": 34,
		"eyeColor": "blue",
		"name": "Kathrine Leblanc",
		"gender": "female",
		"email": "kathrineleblanc@euron.com",
		"phone": "+1 (996) 473-2519"
	},

	{
		"_id": "57b3f46b609bd60868b512f8",
		"index": 28,
		"age": 26,
		"eyeColor": "brown",
		"name": "Kimberley Riley",
		"gender": "female",
		"email": "kimberleyriley@euron.com",
		"phone": "+1 (896) 460-2997"
	},

	{
		"_id": "57b3f46b113dccc67cb7c105",
		"index": 29,
		"age": 31,
		"eyeColor": "green",
		"name": "Allyson Potts",
		"gender": "female",
		"email": "allysonpotts@euron.com",
		"phone": "+1 (998) 415-3330"
	},

	{
		"_id": "57b3f46b6ca5d9b8c32ae356",
		"index": 30,
		"age": 32,
		"eyeColor": "brown",
		"name": "Sweeney Conley",
		"gender": "male",
		"email": "sweeneyconley@euron.com",
		"phone": "+1 (827) 550-3901"
	},

	{
		"_id": "57b3f46be04dcb2cbc8d76cb",
		"index": 31,
		"age": 34,
		"eyeColor": "brown",
		"name": "Natalia Johnson",
		"gender": "female",
		"email": "nataliajohnson@euron.com",
		"phone": "+1 (951) 536-3937"
	},

	{
		"_id": "57b3f46b66e064194b679f79",
		"index": 32,
		"age": 37,
		"eyeColor": "brown",
		"name": "Rosalyn Gallagher",
		"gender": "female",
		"email": "rosalyngallagher@euron.com",
		"phone": "+1 (811) 572-3917"
	},

	{
		"_id": "57b3f46ba9e064106532f1cc",
		"index": 33,
		"age": 29,
		"eyeColor": "brown",
		"name": "Flossie Zamora",
		"gender": "female",
		"email": "flossiezamora@euron.com",
		"phone": "+1 (837) 549-2349"
	},

	{
		"_id": "57b3f46bf4ff0f08a6935223",
		"index": 34,
		"age": 22,
		"eyeColor": "green",
		"name": "Cannon Stone",
		"gender": "male",
		"email": "cannonstone@euron.com",
		"phone": "+1 (818) 461-3189"
	},

	{
		"_id": "57b3f46bd9c418fd8873f660",
		"index": 35,
		"age": 29,
		"eyeColor": "blue",
		"name": "Ferrell Robbins",
		"gender": "male",
		"email": "ferrellrobbins@euron.com",
		"phone": "+1 (932) 586-3375"
	},

	{
		"_id": "57b3f46b538daf5c8a27a379",
		"index": 36,
		"age": 36,
		"eyeColor": "blue",
		"name": "Meagan Case",
		"gender": "female",
		"email": "meagancase@euron.com",
		"phone": "+1 (868) 567-3900"
	},

	{
		"_id": "57b3f46bab36c02d68d605a1",
		"index": 37,
		"age": 30,
		"eyeColor": "blue",
		"name": "Adeline Roth",
		"gender": "female",
		"email": "adelineroth@euron.com",
		"phone": "+1 (963) 499-3739"
	},

	{
		"_id": "57b3f46be150e120a0d2b745",
		"index": 38,
		"age": 35,
		"eyeColor": "brown",
		"name": "Wilder Jordan",
		"gender": "male",
		"email": "wilderjordan@euron.com",
		"phone": "+1 (895) 560-3941"
	},

	{
		"_id": "57b3f46b37370f4006f32f14",
		"index": 39,
		"age": 40,
		"eyeColor": "green",
		"name": "Ora Garrett",
		"gender": "female",
		"email": "oragarrett@euron.com",
		"phone": "+1 (976) 419-3122"
	},

	{
		"_id": "57b3f46b92120beec89dfc17",
		"index": 40,
		"age": 33,
		"eyeColor": "brown",
		"name": "Mandy French",
		"gender": "female",
		"email": "mandyfrench@euron.com",
		"phone": "+1 (850) 431-2278"
	},

	{
		"_id": "57b3f46b5b905110e5a4459d",
		"index": 41,
		"age": 24,
		"eyeColor": "green",
		"name": "Graciela Decker",
		"gender": "female",
		"email": "gracieladecker@euron.com",
		"phone": "+1 (847) 433-2859"
	},

	{
		"_id": "57b3f46b5dafc485fcdb8036",
		"index": 42,
		"age": 37,
		"eyeColor": "brown",
		"name": "Alta Lawrence",
		"gender": "female",
		"email": "altalawrence@euron.com",
		"phone": "+1 (837) 527-2467"
	},

	{
		"_id": "57b3f46bc988629711fa9777",
		"index": 43,
		"age": 35,
		"eyeColor": "brown",
		"name": "Mills Velazquez",
		"gender": "male",
		"email": "millsvelazquez@euron.com",
		"phone": "+1 (986) 568-3466"
	},

	{
		"_id": "57b3f46bea1547d57903c060",
		"index": 44,
		"age": 21,
		"eyeColor": "green",
		"name": "Benson Cochran",
		"gender": "male",
		"email": "bensoncochran@euron.com",
		"phone": "+1 (862) 416-2863"
	},

	{
		"_id": "57b3f46be26aa5d185a0bfe3",
		"index": 45,
		"age": 38,
		"eyeColor": "blue",
		"name": "Haynes Joyce",
		"gender": "male",
		"email": "haynesjoyce@euron.com",
		"phone": "+1 (981) 435-3862"
	},

	{
		"_id": "57b3f46b776dd4089147624b",
		"index": 46,
		"age": 27,
		"eyeColor": "green",
		"name": "Suzette Mueller",
		"gender": "female",
		"email": "suzettemueller@euron.com",
		"phone": "+1 (860) 551-3299"
	},

	{
		"_id": "57b3f46bf9d543979316096f",
		"index": 47,
		"age": 36,
		"eyeColor": "blue",
		"name": "Hill Fields",
		"gender": "male",
		"email": "hillfields@euron.com",
		"phone": "+1 (861) 411-3886"
	},

	{
		"_id": "57b3f46b9794362214ad4093",
		"index": 48,
		"age": 22,
		"eyeColor": "brown",
		"name": "Hattie English",
		"gender": "female",
		"email": "hattieenglish@euron.com",
		"phone": "+1 (853) 518-2659"
	},

	{
		"_id": "57b3f46b2c9f7dac5bc93a0e",
		"index": 49,
		"age": 24,
		"eyeColor": "blue",
		"name": "Farley Robles",
		"gender": "male",
		"email": "farleyrobles@euron.com",
		"phone": "+1 (948) 591-3838"
	},

	{
		"_id": "57b3f46b51b553c65a6d3177",
		"index": 50,
		"age": 23,
		"eyeColor": "green",
		"name": "Mckenzie Roy",
		"gender": "male",
		"email": "mckenzieroy@euron.com",
		"phone": "+1 (854) 500-3060"
	},

	{
		"_id": "57b3f46b018d5249e5d04847",
		"index": 51,
		"age": 33,
		"eyeColor": "blue",
		"name": "Huffman Weiss",
		"gender": "male",
		"email": "huffmanweiss@euron.com",
		"phone": "+1 (987) 566-3295"
	},

	{
		"_id": "57b3f46b9487c11f2b05a4a3",
		"index": 52,
		"age": 34,
		"eyeColor": "green",
		"name": "Jeannette Campos",
		"gender": "female",
		"email": "jeannettecampos@euron.com",
		"phone": "+1 (934) 472-3025"
	},

	{
		"_id": "57b3f46bf6424d4600cc445d",
		"index": 53,
		"age": 25,
		"eyeColor": "blue",
		"name": "Robinson Contreras",
		"gender": "male",
		"email": "robinsoncontreras@euron.com",
		"phone": "+1 (817) 571-3638"
	},

	{
		"_id": "57b3f46bca6fbd01bedc6294",
		"index": 54,
		"age": 27,
		"eyeColor": "brown",
		"name": "Annie Rodgers",
		"gender": "female",
		"email": "annierodgers@euron.com",
		"phone": "+1 (882) 540-3517"
	},

	{
		"_id": "57b3f46b54ab1f5eecfa8040",
		"index": 55,
		"age": 30,
		"eyeColor": "green",
		"name": "Madeleine Mcguire",
		"gender": "female",
		"email": "madeleinemcguire@euron.com",
		"phone": "+1 (819) 441-2372"
	},

	{
		"_id": "57b3f46ba4ea935b1cacc0df",
		"index": 56,
		"age": 35,
		"eyeColor": "brown",
		"name": "Cross Stokes",
		"gender": "male",
		"email": "crossstokes@euron.com",
		"phone": "+1 (919) 569-3542"
	},

	{
		"_id": "57b3f46b37d14ee6f03e41dd",
		"index": 57,
		"age": 29,
		"eyeColor": "brown",
		"name": "Schwartz Blanchard",
		"gender": "male",
		"email": "schwartzblanchard@euron.com",
		"phone": "+1 (925) 550-3878"
	},

	{
		"_id": "57b3f46b0b7c893ead0a4c50",
		"index": 58,
		"age": 27,
		"eyeColor": "blue",
		"name": "Jerry Nichols",
		"gender": "female",
		"email": "jerrynichols@euron.com",
		"phone": "+1 (852) 587-3818"
	},

	{
		"_id": "57b3f46bda2407ac92d07652",
		"index": 59,
		"age": 20,
		"eyeColor": "blue",
		"name": "Baker Mcintyre",
		"gender": "male",
		"email": "bakermcintyre@euron.com",
		"phone": "+1 (870) 424-3654"
	},

	{
		"_id": "57b3f46b125b414524102614",
		"index": 60,
		"age": 28,
		"eyeColor": "brown",
		"name": "Jefferson Melendez",
		"gender": "male",
		"email": "jeffersonmelendez@euron.com",
		"phone": "+1 (927) 423-3044"
	},

	{
		"_id": "57b3f46b03b9dba207ded389",
		"index": 61,
		"age": 31,
		"eyeColor": "brown",
		"name": "Gena Valencia",
		"gender": "female",
		"email": "genavalencia@euron.com",
		"phone": "+1 (809) 507-3518"
	},

	{
		"_id": "57b3f46be9c4e744593e70c8",
		"index": 62,
		"age": 33,
		"eyeColor": "blue",
		"name": "Stephanie Peterson",
		"gender": "female",
		"email": "stephaniepeterson@euron.com",
		"phone": "+1 (982) 528-3326"
	},

	{
		"_id": "57b3f46b31947da865c26c94",
		"index": 63,
		"age": 31,
		"eyeColor": "green",
		"name": "Walters Reid",
		"gender": "male",
		"email": "waltersreid@euron.com",
		"phone": "+1 (839) 529-3373"
	},

	{
		"_id": "57b3f46b51d783a7eb95ed2f",
		"index": 64,
		"age": 30,
		"eyeColor": "green",
		"name": "Gabriela Macias",
		"gender": "female",
		"email": "gabrielamacias@euron.com",
		"phone": "+1 (876) 464-3283"
	},

	{
		"_id": "57b3f46be701ccaeb95180a0",
		"index": 65,
		"age": 40,
		"eyeColor": "blue",
		"name": "Farmer Hicks",
		"gender": "male",
		"email": "farmerhicks@euron.com",
		"phone": "+1 (923) 575-3248"
	},

	{
		"_id": "57b3f46b36f04b24aa91c98e",
		"index": 66,
		"age": 40,
		"eyeColor": "green",
		"name": "Butler Bray",
		"gender": "male",
		"email": "butlerbray@euron.com",
		"phone": "+1 (862) 486-3861"
	},

	{
		"_id": "57b3f46b94d454ddba73736c",
		"index": 67,
		"age": 29,
		"eyeColor": "blue",
		"name": "Hopper Howe",
		"gender": "male",
		"email": "hopperhowe@euron.com",
		"phone": "+1 (997) 507-2568"
	},

	{
		"_id": "57b3f46b0f367ab34b6c870e",
		"index": 68,
		"age": 23,
		"eyeColor": "green",
		"name": "Lorena Figueroa",
		"gender": "female",
		"email": "lorenafigueroa@euron.com",
		"phone": "+1 (951) 590-3639"
	},

	{
		"_id": "57b3f46b7e90c15cb5d1bc70",
		"index": 69,
		"age": 31,
		"eyeColor": "blue",
		"name": "Chen Ayers",
		"gender": "male",
		"email": "chenayers@euron.com",
		"phone": "+1 (989) 584-2479"
	},

	{
		"_id": "57b3f46bc42acbf75b351bc4",
		"index": 70,
		"age": 20,
		"eyeColor": "blue",
		"name": "Inez Brown",
		"gender": "female",
		"email": "inezbrown@euron.com",
		"phone": "+1 (902) 521-3761"
	},

	{
		"_id": "57b3f46b3929b847fa708bcf",
		"index": 71,
		"age": 40,
		"eyeColor": "green",
		"name": "Rios Bonner",
		"gender": "male",
		"email": "riosbonner@euron.com",
		"phone": "+1 (958) 419-3886"
	},

	{
		"_id": "57b3f46b9cd9c68e33b3c44f",
		"index": 72,
		"age": 34,
		"eyeColor": "blue",
		"name": "Santos Henson",
		"gender": "male",
		"email": "santoshenson@euron.com",
		"phone": "+1 (854) 460-3736"
	},

	{
		"_id": "57b3f46b10565427ca241a6b",
		"index": 73,
		"age": 23,
		"eyeColor": "brown",
		"name": "Noelle Ewing",
		"gender": "female",
		"email": "noelleewing@euron.com",
		"phone": "+1 (814) 445-2727"
	},

	{
		"_id": "57b3f46bda4fabdff06860ca",
		"index": 74,
		"age": 23,
		"eyeColor": "blue",
		"name": "Pollard Lyons",
		"gender": "male",
		"email": "pollardlyons@euron.com",
		"phone": "+1 (927) 549-2840"
	},

	{
		"_id": "57b3f46b3961d25ddfc325c3",
		"index": 75,
		"age": 26,
		"eyeColor": "blue",
		"name": "Abigail Forbes",
		"gender": "female",
		"email": "abigailforbes@euron.com",
		"phone": "+1 (812) 407-2067"
	},

	{
		"_id": "57b3f46b642d7c06196107b2",
		"index": 76,
		"age": 37,
		"eyeColor": "blue",
		"name": "Atkinson Soto",
		"gender": "male",
		"email": "atkinsonsoto@euron.com",
		"phone": "+1 (831) 523-2433"
	},

	{
		"_id": "57b3f46b6a6f7ed49d095812",
		"index": 77,
		"age": 32,
		"eyeColor": "blue",
		"name": "Petra Montoya",
		"gender": "female",
		"email": "petramontoya@euron.com",
		"phone": "+1 (897) 425-3905"
	},

	{
		"_id": "57b3f46b89c75a4bc978dc75",
		"index": 78,
		"age": 38,
		"eyeColor": "green",
		"name": "Lucile Bullock",
		"gender": "female",
		"email": "lucilebullock@euron.com",
		"phone": "+1 (953) 518-3846"
	},

	{
		"_id": "57b3f46b99fd0da8697c0794",
		"index": 79,
		"age": 32,
		"eyeColor": "brown",
		"name": "Lessie Yang",
		"gender": "female",
		"email": "lessieyang@euron.com",
		"phone": "+1 (837) 494-3987"
	},

	{
		"_id": "57b3f46b51ef9ed004b30c58",
		"index": 80,
		"age": 30,
		"eyeColor": "brown",
		"name": "Annette Flores",
		"gender": "female",
		"email": "annetteflores@euron.com",
		"phone": "+1 (918) 558-3834"
	},

	{
		"_id": "57b3f46b47508b2cd620526b",
		"index": 81,
		"age": 40,
		"eyeColor": "green",
		"name": "Marion Chase",
		"gender": "female",
		"email": "marionchase@euron.com",
		"phone": "+1 (893) 530-2901"
	},

	{
		"_id": "57b3f46b7e68f5d8b1f27734",
		"index": 82,
		"age": 31,
		"eyeColor": "blue",
		"name": "Abbott Davenport",
		"gender": "male",
		"email": "abbottdavenport@euron.com",
		"phone": "+1 (942) 532-2634"
	},

	{
		"_id": "57b3f46b9fa10afac1ce6e31",
		"index": 83,
		"age": 34,
		"eyeColor": "brown",
		"name": "Bianca Hall",
		"gender": "female",
		"email": "biancahall@euron.com",
		"phone": "+1 (920) 522-3578"
	},

	{
		"_id": "57b3f46bbf939c1209bdcb3e",
		"index": 84,
		"age": 37,
		"eyeColor": "green",
		"name": "Shirley Mcmillan",
		"gender": "female",
		"email": "shirleymcmillan@euron.com",
		"phone": "+1 (836) 444-3338"
	},

	{
		"_id": "57b3f46ba0a47a938405c650",
		"index": 85,
		"age": 25,
		"eyeColor": "blue",
		"name": "Lou Best",
		"gender": "female",
		"email": "loubest@euron.com",
		"phone": "+1 (919) 444-2012"
	},

	{
		"_id": "57b3f46bd05fd2afa701dca6",
		"index": 86,
		"age": 22,
		"eyeColor": "brown",
		"name": "Kayla Hebert",
		"gender": "female",
		"email": "kaylahebert@euron.com",
		"phone": "+1 (961) 471-3069"
	},

	{
		"_id": "57b3f46b672fe8ad0bf75d9a",
		"index": 87,
		"age": 25,
		"eyeColor": "green",
		"name": "Celina Leach",
		"gender": "female",
		"email": "celinaleach@euron.com",
		"phone": "+1 (841) 496-2117"
	},

	{
		"_id": "57b3f46bfbab71153de89400",
		"index": 88,
		"age": 38,
		"eyeColor": "brown",
		"name": "Dodson Douglas",
		"gender": "male",
		"email": "dodsondouglas@euron.com",
		"phone": "+1 (830) 450-2028"
	},

	{
		"_id": "57b3f46bb1c823531170db5c",
		"index": 89,
		"age": 33,
		"eyeColor": "blue",
		"name": "Dionne Berg",
		"gender": "female",
		"email": "dionneberg@euron.com",
		"phone": "+1 (862) 520-2043"
	},

	{
		"_id": "57b3f46bd20c771721cf4b65",
		"index": 90,
		"age": 38,
		"eyeColor": "green",
		"name": "Brianna Odom",
		"gender": "female",
		"email": "briannaodom@euron.com",
		"phone": "+1 (838) 417-2355"
	},

	{
		"_id": "57b3f46baa2b48b8ccf6a445",
		"index": 91,
		"age": 21,
		"eyeColor": "blue",
		"name": "Sheena Kidd",
		"gender": "female",
		"email": "sheenakidd@euron.com",
		"phone": "+1 (922) 580-3410"
	},

	{
		"_id": "57b3f46bc53913d3e304517f",
		"index": 92,
		"age": 21,
		"eyeColor": "brown",
		"name": "Barker Lindsay",
		"gender": "male",
		"email": "barkerlindsay@euron.com",
		"phone": "+1 (879) 578-3890"
	},

	{
		"_id": "57b3f46b7875bd5ef6890c7c",
		"index": 93,
		"age": 22,
		"eyeColor": "green",
		"name": "Kay Klein",
		"gender": "female",
		"email": "kayklein@euron.com",
		"phone": "+1 (925) 524-3363"
	},

	{
		"_id": "57b3f46b40d9f9a5697fe9ef",
		"index": 94,
		"age": 35,
		"eyeColor": "brown",
		"name": "Claudia Randolph",
		"gender": "female",
		"email": "claudiarandolph@euron.com",
		"phone": "+1 (858) 580-3692"
	},

	{
		"_id": "57b3f46bf6fe0f905b993754",
		"index": 95,
		"age": 35,
		"eyeColor": "blue",
		"name": "Collier Stephenson",
		"gender": "male",
		"email": "collierstephenson@euron.com",
		"phone": "+1 (952) 540-3709"
	},

	{
		"_id": "57b3f46b44611e912db7c9df",
		"index": 96,
		"age": 24,
		"eyeColor": "brown",
		"name": "Hart Sloan",
		"gender": "male",
		"email": "hartsloan@euron.com",
		"phone": "+1 (875) 549-2694"
	},

	{
		"_id": "57b3f46b8bc2815111a4320d",
		"index": 97,
		"age": 27,
		"eyeColor": "blue",
		"name": "Maynard Neal",
		"gender": "male",
		"email": "maynardneal@euron.com",
		"phone": "+1 (845) 479-2978"
	},

	{
		"_id": "57b3f46b1007b7541e88b23f",
		"index": 98,
		"age": 34,
		"eyeColor": "brown",
		"name": "Frankie Guy",
		"gender": "female",
		"email": "frankieguy@euron.com",
		"phone": "+1 (873) 500-2545"
	},

	{
		"_id": "57b3f46b55edafd71ba9f11b",
		"index": 99,
		"age": 23,
		"eyeColor": "brown",
		"name": "Jana Moses",
		"gender": "female",
		"email": "janamoses@euron.com",
		"phone": "+1 (820) 454-3934"
	},

	{
		"_id": "57b3f46b6f5d1f095f07df0a",
		"index": 100,
		"age": 33,
		"eyeColor": "green",
		"name": "Denise Carr",
		"gender": "female",
		"email": "denisecarr@euron.com",
		"phone": "+1 (923) 592-2534"
	},

	{
		"_id": "57b3f46b41c708d15846620c",
		"index": 101,
		"age": 32,
		"eyeColor": "green",
		"name": "Shauna Blankenship",
		"gender": "female",
		"email": "shaunablankenship@euron.com",
		"phone": "+1 (938) 431-2479"
	},

	{
		"_id": "57b3f46b44025f04b4df192f",
		"index": 102,
		"age": 34,
		"eyeColor": "green",
		"name": "Beck Whitley",
		"gender": "male",
		"email": "beckwhitley@euron.com",
		"phone": "+1 (875) 497-3563"
	},

	{
		"_id": "57b3f46b778be44387ef901e",
		"index": 103,
		"age": 38,
		"eyeColor": "brown",
		"name": "Craft Acosta",
		"gender": "male",
		"email": "craftacosta@euron.com",
		"phone": "+1 (807) 501-3887"
	},

	{
		"_id": "57b3f46b59e602c6048d9fa1",
		"index": 104,
		"age": 31,
		"eyeColor": "green",
		"name": "Nannie Odonnell",
		"gender": "female",
		"email": "nannieodonnell@euron.com",
		"phone": "+1 (812) 519-3646"
	},

	{
		"_id": "57b3f46b2536e3a4c91a29c4",
		"index": 105,
		"age": 21,
		"eyeColor": "green",
		"name": "Lee Knapp",
		"gender": "female",
		"email": "leeknapp@euron.com",
		"phone": "+1 (937) 504-2873"
	},

	{
		"_id": "57b3f46b533e9b6699eb902f",
		"index": 106,
		"age": 27,
		"eyeColor": "green",
		"name": "Bray Gilbert",
		"gender": "male",
		"email": "braygilbert@euron.com",
		"phone": "+1 (921) 441-3033"
	},

	{
		"_id": "57b3f46b46d84b320c35821c",
		"index": 107,
		"age": 26,
		"eyeColor": "blue",
		"name": "Gill Finch",
		"gender": "male",
		"email": "gillfinch@euron.com",
		"phone": "+1 (948) 572-2926"
	},

	{
		"_id": "57b3f46b7e36458013f9753e",
		"index": 108,
		"age": 23,
		"eyeColor": "blue",
		"name": "Giles Ratliff",
		"gender": "male",
		"email": "gilesratliff@euron.com",
		"phone": "+1 (923) 519-2365"
	},

	{
		"_id": "57b3f46badc56d6d81fbaad4",
		"index": 109,
		"age": 28,
		"eyeColor": "brown",
		"name": "Esperanza Frye",
		"gender": "female",
		"email": "esperanzafrye@euron.com",
		"phone": "+1 (873) 576-2256"
	},

	{
		"_id": "57b3f46be95be1ce18681e37",
		"index": 110,
		"age": 38,
		"eyeColor": "blue",
		"name": "Sallie Parsons",
		"gender": "female",
		"email": "sallieparsons@euron.com",
		"phone": "+1 (857) 472-2365"
	},

	{
		"_id": "57b3f46ba4e4bb99f9fa491c",
		"index": 111,
		"age": 24,
		"eyeColor": "blue",
		"name": "Carey Hooper",
		"gender": "female",
		"email": "careyhooper@euron.com",
		"phone": "+1 (823) 503-2264"
	},

	{
		"_id": "57b3f46beb5226a159f0e6d1",
		"index": 112,
		"age": 21,
		"eyeColor": "green",
		"name": "Traci Small",
		"gender": "female",
		"email": "tracismall@euron.com",
		"phone": "+1 (866) 473-2483"
	},

	{
		"_id": "57b3f46be7f84de0812f88c7",
		"index": 113,
		"age": 21,
		"eyeColor": "green",
		"name": "Valenzuela Pace",
		"gender": "male",
		"email": "valenzuelapace@euron.com",
		"phone": "+1 (915) 401-2515"
	},

	{
		"_id": "57b3f46b5b271b1438b3f267",
		"index": 114,
		"age": 27,
		"eyeColor": "blue",
		"name": "Josefa Morton",
		"gender": "female",
		"email": "josefamorton@euron.com",
		"phone": "+1 (837) 560-3221"
	},

	{
		"_id": "57b3f46b800ffd04261b77cb",
		"index": 115,
		"age": 37,
		"eyeColor": "brown",
		"name": "Ortega Mendoza",
		"gender": "male",
		"email": "ortegamendoza@euron.com",
		"phone": "+1 (872) 594-3690"
	},

	{
		"_id": "57b3f46bf266a03891ba7b45",
		"index": 116,
		"age": 39,
		"eyeColor": "green",
		"name": "Simpson Kirk",
		"gender": "male",
		"email": "simpsonkirk@euron.com",
		"phone": "+1 (846) 583-3905"
	},

	{
		"_id": "57b3f46be67242c61104c70e",
		"index": 117,
		"age": 32,
		"eyeColor": "blue",
		"name": "Kris Grimes",
		"gender": "female",
		"email": "krisgrimes@euron.com",
		"phone": "+1 (936) 560-2217"
	},

	{
		"_id": "57b3f46b7f5a4a1f57213256",
		"index": 118,
		"age": 32,
		"eyeColor": "brown",
		"name": "Roseann Hammond",
		"gender": "female",
		"email": "roseannhammond@euron.com",
		"phone": "+1 (870) 496-2245"
	},

	{
		"_id": "57b3f46b60c1e29f17d4bb5b",
		"index": 119,
		"age": 21,
		"eyeColor": "green",
		"name": "Sheila Keith",
		"gender": "female",
		"email": "sheilakeith@euron.com",
		"phone": "+1 (809) 581-2827"
	},

	{
		"_id": "57b3f46b1ca89554fe37c66b",
		"index": 120,
		"age": 30,
		"eyeColor": "green",
		"name": "Marilyn Wilcox",
		"gender": "female",
		"email": "marilynwilcox@euron.com",
		"phone": "+1 (960) 530-3777"
	},

	{
		"_id": "57b3f46b279843a48528af21",
		"index": 121,
		"age": 40,
		"eyeColor": "brown",
		"name": "Raymond Cummings",
		"gender": "male",
		"email": "raymondcummings@euron.com",
		"phone": "+1 (907) 545-3324"
	},

	{
		"_id": "57b3f46b9a0db2076c867025",
		"index": 122,
		"age": 20,
		"eyeColor": "blue",
		"name": "Leona Stafford",
		"gender": "female",
		"email": "leonastafford@euron.com",
		"phone": "+1 (935) 472-2386"
	},

	{
		"_id": "57b3f46bf492c2e9b1b09e8a",
		"index": 123,
		"age": 20,
		"eyeColor": "green",
		"name": "Ilene Nixon",
		"gender": "female",
		"email": "ilenenixon@euron.com",
		"phone": "+1 (839) 422-2178"
	},

	{
		"_id": "57b3f46b05f8c8606d96976e",
		"index": 124,
		"age": 33,
		"eyeColor": "green",
		"name": "Snider Lane",
		"gender": "male",
		"email": "sniderlane@euron.com",
		"phone": "+1 (874) 472-3371"
	},

	{
		"_id": "57b3f46b55e8be608c2137f8",
		"index": 125,
		"age": 27,
		"eyeColor": "blue",
		"name": "Stefanie Holt",
		"gender": "female",
		"email": "stefanieholt@euron.com",
		"phone": "+1 (994) 400-2892"
	},

	{
		"_id": "57b3f46bb5327abdb12b375e",
		"index": 126,
		"age": 29,
		"eyeColor": "green",
		"name": "Olsen Calhoun",
		"gender": "male",
		"email": "olsencalhoun@euron.com",
		"phone": "+1 (819) 513-2872"
	},

	{
		"_id": "57b3f46bed2a40cec442c1c3",
		"index": 127,
		"age": 35,
		"eyeColor": "brown",
		"name": "Manuela Cox",
		"gender": "female",
		"email": "manuelacox@euron.com",
		"phone": "+1 (811) 480-3253"
	},

	{
		"_id": "57b3f46b63aaba7064892c7a",
		"index": 128,
		"age": 28,
		"eyeColor": "brown",
		"name": "Rivers Mccormick",
		"gender": "male",
		"email": "riversmccormick@euron.com",
		"phone": "+1 (942) 565-2782"
	},

	{
		"_id": "57b3f46bcb64c98a7ef3d4f0",
		"index": 129,
		"age": 24,
		"eyeColor": "blue",
		"name": "Nicholson Briggs",
		"gender": "male",
		"email": "nicholsonbriggs@euron.com",
		"phone": "+1 (844) 433-3302"
	},

	{
		"_id": "57b3f46b84df4ecf99e7c262",
		"index": 130,
		"age": 34,
		"eyeColor": "brown",
		"name": "Dyer Haney",
		"gender": "male",
		"email": "dyerhaney@euron.com",
		"phone": "+1 (975) 452-2092"
	},

	{
		"_id": "57b3f46ba2c1fe6daf24d9f9",
		"index": 131,
		"age": 34,
		"eyeColor": "green",
		"name": "Weber Dean",
		"gender": "male",
		"email": "weberdean@euron.com",
		"phone": "+1 (846) 421-3973"
	},

	{
		"_id": "57b3f46b81950e5e5676de87",
		"index": 132,
		"age": 22,
		"eyeColor": "brown",
		"name": "Cox Hess",
		"gender": "male",
		"email": "coxhess@euron.com",
		"phone": "+1 (855) 528-3640"
	},

	{
		"_id": "57b3f46b3e8f509e053d2991",
		"index": 133,
		"age": 35,
		"eyeColor": "brown",
		"name": "Noreen Wilkins",
		"gender": "female",
		"email": "noreenwilkins@euron.com",
		"phone": "+1 (925) 539-3720"
	},

	{
		"_id": "57b3f46b07d7260a30e27a79",
		"index": 134,
		"age": 20,
		"eyeColor": "green",
		"name": "Yang Gamble",
		"gender": "male",
		"email": "yanggamble@euron.com",
		"phone": "+1 (943) 479-3678"
	},

	{
		"_id": "57b3f46baa2e70068bb7b1cf",
		"index": 135,
		"age": 37,
		"eyeColor": "brown",
		"name": "Priscilla Gould",
		"gender": "female",
		"email": "priscillagould@euron.com",
		"phone": "+1 (853) 556-2606"
	},

	{
		"_id": "57b3f46b73770791995b7e39",
		"index": 136,
		"age": 29,
		"eyeColor": "green",
		"name": "Porter Barrera",
		"gender": "male",
		"email": "porterbarrera@euron.com",
		"phone": "+1 (857) 541-2203"
	},

	{
		"_id": "57b3f46b397ce7e0e1649255",
		"index": 137,
		"age": 22,
		"eyeColor": "blue",
		"name": "Carissa Maxwell",
		"gender": "female",
		"email": "carissamaxwell@euron.com",
		"phone": "+1 (875) 599-3225"
	},

	{
		"_id": "57b3f46bf08b4dc46ca24a6f",
		"index": 138,
		"age": 20,
		"eyeColor": "brown",
		"name": "Dorothy Pena",
		"gender": "female",
		"email": "dorothypena@euron.com",
		"phone": "+1 (908) 443-3267"
	},

	{
		"_id": "57b3f46bc066df195694e6fb",
		"index": 139,
		"age": 30,
		"eyeColor": "brown",
		"name": "Dee Cunningham",
		"gender": "female",
		"email": "deecunningham@euron.com",
		"phone": "+1 (978) 532-3743"
	},

	{
		"_id": "57b3f46b9ffb6b926e394434",
		"index": 140,
		"age": 34,
		"eyeColor": "green",
		"name": "Crosby Lambert",
		"gender": "male",
		"email": "crosbylambert@euron.com",
		"phone": "+1 (902) 491-2595"
	},

	{
		"_id": "57b3f46b5b583eb366b79084",
		"index": 141,
		"age": 28,
		"eyeColor": "brown",
		"name": "Sherry Greene",
		"gender": "female",
		"email": "sherrygreene@euron.com",
		"phone": "+1 (859) 511-3402"
	},

	{
		"_id": "57b3f46b89761c7d6c298198",
		"index": 142,
		"age": 21,
		"eyeColor": "blue",
		"name": "Gayle Webb",
		"gender": "female",
		"email": "gaylewebb@euron.com",
		"phone": "+1 (922) 571-2711"
	},

	{
		"_id": "57b3f46ba05908b4fad96960",
		"index": 143,
		"age": 40,
		"eyeColor": "green",
		"name": "West Fuller",
		"gender": "male",
		"email": "westfuller@euron.com",
		"phone": "+1 (879) 499-3872"
	},

	{
		"_id": "57b3f46b5f0debf9456266bc",
		"index": 144,
		"age": 32,
		"eyeColor": "blue",
		"name": "Britt Crawford",
		"gender": "male",
		"email": "brittcrawford@euron.com",
		"phone": "+1 (821) 418-3360"
	},

	{
		"_id": "57b3f46be1246eaf6a400f1c",
		"index": 145,
		"age": 35,
		"eyeColor": "blue",
		"name": "Alexandria Mckenzie",
		"gender": "female",
		"email": "alexandriamckenzie@euron.com",
		"phone": "+1 (933) 494-2839"
	},

	{
		"_id": "57b3f46b31df6d8980b33286",
		"index": 146,
		"age": 25,
		"eyeColor": "brown",
		"name": "Iva Hamilton",
		"gender": "female",
		"email": "ivahamilton@euron.com",
		"phone": "+1 (906) 488-2457"
	},

	{
		"_id": "57b3f46b13c9804f0e579de4",
		"index": 147,
		"age": 28,
		"eyeColor": "blue",
		"name": "Evangeline Massey",
		"gender": "female",
		"email": "evangelinemassey@euron.com",
		"phone": "+1 (996) 460-3422"
	},

	{
		"_id": "57b3f46b700db4dace06a1f4",
		"index": 148,
		"age": 24,
		"eyeColor": "blue",
		"name": "Gloria Roberts",
		"gender": "female",
		"email": "gloriaroberts@euron.com",
		"phone": "+1 (913) 506-3707"
	},

	{
		"_id": "57b3f46b32a499abc4a5579c",
		"index": 149,
		"age": 36,
		"eyeColor": "brown",
		"name": "Perry Patton",
		"gender": "male",
		"email": "perrypatton@euron.com",
		"phone": "+1 (865) 408-2891"
	},

	{
		"_id": "57b3f46b84614612dc57e23b",
		"index": 150,
		"age": 32,
		"eyeColor": "brown",
		"name": "Marquez Austin",
		"gender": "male",
		"email": "marquezaustin@euron.com",
		"phone": "+1 (909) 550-2685"
	},

	{
		"_id": "57b3f46bb86583bdf7a8af1a",
		"index": 151,
		"age": 39,
		"eyeColor": "blue",
		"name": "Leanna Wyatt",
		"gender": "female",
		"email": "leannawyatt@euron.com",
		"phone": "+1 (804) 522-2058"
	},

	{
		"_id": "57b3f46b7b64f8dbc6adb26c",
		"index": 152,
		"age": 29,
		"eyeColor": "green",
		"name": "Rebecca Wade",
		"gender": "female",
		"email": "rebeccawade@euron.com",
		"phone": "+1 (896) 575-2448"
	},

	{
		"_id": "57b3f46b3751c4571ea90697",
		"index": 153,
		"age": 35,
		"eyeColor": "blue",
		"name": "Phoebe Benton",
		"gender": "female",
		"email": "phoebebenton@euron.com",
		"phone": "+1 (965) 410-2930"
	},

	{
		"_id": "57b3f46bb8818673b2bab687",
		"index": 154,
		"age": 22,
		"eyeColor": "brown",
		"name": "Mcleod Ochoa",
		"gender": "male",
		"email": "mcleodochoa@euron.com",
		"phone": "+1 (912) 420-3085"
	},

	{
		"_id": "57b3f46b3ee5cc329ea41239",
		"index": 155,
		"age": 38,
		"eyeColor": "green",
		"name": "Pearlie Solomon",
		"gender": "female",
		"email": "pearliesolomon@euron.com",
		"phone": "+1 (801) 466-3984"
	},

	{
		"_id": "57b3f46b554af653068b1af9",
		"index": 156,
		"age": 32,
		"eyeColor": "blue",
		"name": "Grant Rich",
		"gender": "male",
		"email": "grantrich@euron.com",
		"phone": "+1 (911) 573-2165"
	},

	{
		"_id": "57b3f46b94def0356c083e2d",
		"index": 157,
		"age": 32,
		"eyeColor": "blue",
		"name": "Dixie Franco",
		"gender": "female",
		"email": "dixiefranco@euron.com",
		"phone": "+1 (985) 490-2562"
	},

	{
		"_id": "57b3f46b958781cab4cf9b02",
		"index": 158,
		"age": 39,
		"eyeColor": "blue",
		"name": "Callie Barrett",
		"gender": "female",
		"email": "calliebarrett@euron.com",
		"phone": "+1 (811) 558-3751"
	},

	{
		"_id": "57b3f46b18428abe3338d753",
		"index": 159,
		"age": 39,
		"eyeColor": "green",
		"name": "Carolyn Dunlap",
		"gender": "female",
		"email": "carolyndunlap@euron.com",
		"phone": "+1 (944) 533-2913"
	},

	{
		"_id": "57b3f46ba31b812366e934c8",
		"index": 160,
		"age": 35,
		"eyeColor": "green",
		"name": "Travis Barlow",
		"gender": "male",
		"email": "travisbarlow@euron.com",
		"phone": "+1 (887) 494-2403"
	},

	{
		"_id": "57b3f46ba002dc478df8c66a",
		"index": 161,
		"age": 23,
		"eyeColor": "green",
		"name": "Shannon Stark",
		"gender": "female",
		"email": "shannonstark@euron.com",
		"phone": "+1 (975) 556-3734"
	},

	{
		"_id": "57b3f46b6b6604fc357cd2cd",
		"index": 162,
		"age": 25,
		"eyeColor": "blue",
		"name": "Marsh Buckley",
		"gender": "male",
		"email": "marshbuckley@euron.com",
		"phone": "+1 (930) 418-2533"
	},

	{
		"_id": "57b3f46b21936fd5211f4eab",
		"index": 163,
		"age": 20,
		"eyeColor": "brown",
		"name": "Estrada Harper",
		"gender": "male",
		"email": "estradaharper@euron.com",
		"phone": "+1 (933) 535-2967"
	},

	{
		"_id": "57b3f46bc4e2dae50da242fe",
		"index": 164,
		"age": 36,
		"eyeColor": "blue",
		"name": "Hubbard Anthony",
		"gender": "male",
		"email": "hubbardanthony@euron.com",
		"phone": "+1 (931) 518-3396"
	},

	{
		"_id": "57b3f46b1a4fe3667190a18a",
		"index": 165,
		"age": 23,
		"eyeColor": "brown",
		"name": "Parrish Dejesus",
		"gender": "male",
		"email": "parrishdejesus@euron.com",
		"phone": "+1 (990) 418-3929"
	},

	{
		"_id": "57b3f46b96cba4f604611394",
		"index": 166,
		"age": 29,
		"eyeColor": "brown",
		"name": "Cote Norton",
		"gender": "male",
		"email": "cotenorton@euron.com",
		"phone": "+1 (835) 517-2848"
	},

	{
		"_id": "57b3f46b46745c9fa13d6a4a",
		"index": 167,
		"age": 27,
		"eyeColor": "green",
		"name": "Berta Bender",
		"gender": "female",
		"email": "bertabender@euron.com",
		"phone": "+1 (826) 563-3977"
	}
	]
}